semantic_release/__init__.py
semantic_release/ci_checks.py
semantic_release/cli.py
semantic_release/defaults.cfg
semantic_release/errors.py
semantic_release/hvcs.py
semantic_release/pypi.py
semantic_release/settings.py
semantic_release/vcs_helpers.py
semantic_release/history/__init__.py
semantic_release/history/logs.py
semantic_release/history/parser_angular.py
semantic_release/history/parser_helpers.py
semantic_release/history/parser_tag.py
tests/ci_checks/__init__.py
tests/ci_checks/test_bitbucket.py
tests/ci_checks/test_checker.py
tests/ci_checks/test_circle.py
tests/ci_checks/test_frigg.py
tests/ci_checks/test_gitlab.py
tests/ci_checks/test_semaphore.py
tests/ci_checks/test_travis.py
tests/parsers/__init__.py
tests/parsers/test_angular.py
tests/parsers/test_helpers.py
tests/parsers/test_tag.py
other_semantic_release-5.0.0.dist-info/AUTHORS.rst
other_semantic_release-5.0.0.dist-info/LICENSE
other_semantic_release-5.0.0.dist-info/METADATA
other_semantic_release-5.0.0.dist-info/WHEEL
other_semantic_release-5.0.0.dist-info/entry_points.txt
other_semantic_release-5.0.0.dist-info/top_level.txt
other_semantic_release-5.0.0.dist-info/RECORD
