Metadata-Version: 2.1
Name: other-semantic-release
Version: 5.0.0
Summary: Automatic semantic versioning for python projects
Home-page: http://github.com/aborsu/other-semantic-release
Author: Augustin Borsu, but really its Rolf Erik Lekang
Author-email: a.borsu@acelpb.com
License: MIT
Platform: UNKNOWN
Classifier: Programming Language :: Python
Classifier: Programming Language :: Python :: 3
Classifier: Programming Language :: Python :: 3.6
Classifier: Programming Language :: Python :: 3.7
Requires-Dist: click (~=6.2)
Requires-Dist: gitpython (~=2.1)
Requires-Dist: semver (~=2.2)
Requires-Dist: twine (~=1.12)
Requires-Dist: requests (~=2.21)
Requires-Dist: wheel
Requires-Dist: ndebug (~=0.1)
